awslabs/__init__.py
awslabs/cost_analysis_mcp_server/__init__.py
awslabs/cost_analysis_mcp_server/cdk_analyzer.py
awslabs/cost_analysis_mcp_server/consts.py
awslabs/cost_analysis_mcp_server/helpers.py
awslabs/cost_analysis_mcp_server/models.py
awslabs/cost_analysis_mcp_server/pricing_client.py
awslabs/cost_analysis_mcp_server/report_generator.py
awslabs/cost_analysis_mcp_server/server.py
awslabs/cost_analysis_mcp_server/terraform_analyzer.py
awslabs/cost_analysis_mcp_server/static/COST_REPORT_TEMPLATE.md
awslabs/cost_analysis_mcp_server/static/__init__.py
awslabs/cost_analysis_mcp_server/static/patterns/BEDROCK.md
awslabs/cost_analysis_mcp_server/static/patterns/__init__.py
awslabs_cost_analysis_mcp_server-1.0.5.dist-info/METADATA
awslabs_cost_analysis_mcp_server-1.0.5.dist-info/WHEEL
awslabs_cost_analysis_mcp_server-1.0.5.dist-info/entry_points.txt
awslabs_cost_analysis_mcp_server-1.0.5.dist-info/licenses/LICENSE
awslabs_cost_analysis_mcp_server-1.0.5.dist-info/licenses/NOTICE
awslabs_cost_analysis_mcp_server-1.0.5.dist-info/RECORD
